SVF
