Metadata-Version: 2.1
Name: SVF
Version: 0.0.2
Summary: Paquete Support Vector Frontier
Home-page: https://github.com/danielvacarre
Author: Daniel Valero Carreras
Author-email: dvalero@umh.es
License: MIT
Platform: UNKNOWN
Classifier: Development Status :: 1 - Planning
Classifier: Intended Audience :: Science/Research
Classifier: Topic :: Scientific/Engineering :: Mathematics
Classifier: License :: OSI Approved :: MIT License
Classifier: Programming Language :: Python :: 3
License-File: LICENSE.txt
